aliyunsdkrtc/__init__.py
aliyunsdkrtc/endpoint.py
aliyunsdkrtc/request/__init__.py
aliyunsdkrtc/request/v20180111/AddRecordTemplateRequest.py
aliyunsdkrtc/request/v20180111/CreateAutoLiveStreamRuleRequest.py
aliyunsdkrtc/request/v20180111/CreateEventSubscribeRequest.py
aliyunsdkrtc/request/v20180111/CreateMPULayoutRequest.py
aliyunsdkrtc/request/v20180111/DeleteAutoLiveStreamRuleRequest.py
aliyunsdkrtc/request/v20180111/DeleteChannelRequest.py
aliyunsdkrtc/request/v20180111/DeleteEventSubscribeRequest.py
aliyunsdkrtc/request/v20180111/DeleteMPULayoutRequest.py
aliyunsdkrtc/request/v20180111/DeleteRecordTemplateRequest.py
aliyunsdkrtc/request/v20180111/DescribeAppKeyRequest.py
aliyunsdkrtc/request/v20180111/DescribeAppsRequest.py
aliyunsdkrtc/request/v20180111/DescribeAutoLiveStreamRuleRequest.py
aliyunsdkrtc/request/v20180111/DescribeChannelParticipantsRequest.py
aliyunsdkrtc/request/v20180111/DescribeChannelUsersRequest.py
aliyunsdkrtc/request/v20180111/DescribeMPULayoutInfoListRequest.py
aliyunsdkrtc/request/v20180111/DescribeRecordFilesRequest.py
aliyunsdkrtc/request/v20180111/DescribeRecordTemplatesRequest.py
aliyunsdkrtc/request/v20180111/DescribeUserInfoInChannelRequest.py
aliyunsdkrtc/request/v20180111/DisableAutoLiveStreamRuleRequest.py
aliyunsdkrtc/request/v20180111/EnableAutoLiveStreamRuleRequest.py
aliyunsdkrtc/request/v20180111/GetMPUTaskStatusRequest.py
aliyunsdkrtc/request/v20180111/ModifyAppRequest.py
aliyunsdkrtc/request/v20180111/ModifyMPULayoutRequest.py
aliyunsdkrtc/request/v20180111/RemoveTerminalsRequest.py
aliyunsdkrtc/request/v20180111/StartMPUTaskRequest.py
aliyunsdkrtc/request/v20180111/StartRecordTaskRequest.py
aliyunsdkrtc/request/v20180111/StopMPUTaskRequest.py
aliyunsdkrtc/request/v20180111/StopRecordTaskRequest.py
aliyunsdkrtc/request/v20180111/UpdateAutoLiveStreamRuleRequest.py
aliyunsdkrtc/request/v20180111/UpdateMPUTaskRequest.py
aliyunsdkrtc/request/v20180111/UpdateRecordTaskRequest.py
aliyun_python_sdk_rtc-1.3.5.dist-info/LICENSE
aliyun_python_sdk_rtc-1.3.5.dist-info/METADATA
aliyun_python_sdk_rtc-1.3.5.dist-info/WHEEL
aliyun_python_sdk_rtc-1.3.5.dist-info/top_level.txt
aliyun_python_sdk_rtc-1.3.5.dist-info/RECORD
